{
  "run_id": "run_20260621_173616",
  "case_id": "GOLD_HASH_H4_30000_train",
  "base_case_id": "GOLD_HASH_H4_30000",
  "phase": "train",
  "symbol": "GOLD#",
  "canonical_symbol": "GOLD",
  "timeframe": "H4",
  "execution_status": "PASS",
  "phase_classification": "VALID_RESULT",
  "case_level_classification": "REJECTED",
  "case_failed_gates": "validation_or_oos_not_positive_valid",
  "report_net_profit": 135.85,
  "report_profit_factor": 2.12,
  "report_relative_drawdown": 0.17,
  "report_total_trades": 30,
  "accepted_signals": 33,
  "rejected_signals": 355,
  "signal_acceptance_rate_pct": 8.51,
  "no_trade_bars": 2700,
  "no_signal_bars": 2191,
  "unsafe_regime_blocks": 509,
  "spread_blocks": 12,
  "max_open_order_blocks": 38,
  "losing_streak_blocks": 0,
  "daily_loss_blocks": 0,
  "weekly_loss_blocks": 0,
  "drawdown_blocks": 0,
  "margin_blocks": 0,
  "stops_level_blocks": 0,
  "freeze_level_blocks": 0,
  "broker_minimum_lot_risk_budget_blocks": 317,
  "buy_count": 275,
  "sell_count": 113,
  "regime_counts": {
    "unsafe": 509,
    "trend": 2093,
    "breakout": 486
  },
  "accepted_regime_counts": {
    "trend": 29,
    "breakout": 4
  },
  "blocked_reason_counts": {
    "broker minimum lot exceeds configured risk budget": 317,
    "max open orders reached": 38
  },
  "no_trade_reason_counts": {
    "unsafe regime: spread too wide": 12,
    "no strategy signal": 2191,
    "unsafe regime: mixed or low-quality conditions": 404,
    "unsafe regime: volatility outside allowed range": 93
  },
  "average_sl_distance": 12.782121,
  "average_tp_distance": 26.556364,
  "average_raw_lot": 0.012252,
  "average_normalized_lot": 0.010606,
  "average_actual_risk_money": 13.084545,
  "average_spread_at_signal_time": null,
  "average_logged_spread": 18.826667,
  "symbol_min_lot": 0.01,
  "symbol_lot_step": 0.01,
  "symbol_tick_size": 0.01,
  "symbol_tick_value": 1.0,
  "symbol_contract_size": 100.0,
  "risk_percent": 0.05,
  "deposit": 30000.0,
  "typical_blocked_raw_lot": 0.0067,
  "typical_blocked_sl_distance": 22.38,
  "estimated_minimum_deposit_for_min_lot": 44776.12,
  "current_deposit_insufficient_for_min_lot": true,
  "suggested_next_deposit_assumption_research_only": 50000,
  "recommendation": "RESEARCH_MORE"
}